LICENSE.md
replacy_issue_boundary/__init__.py
replacy_issue_boundary/boundary.py
replacy_issue_boundary-0.2.12.dist-info/LICENSE.md
replacy_issue_boundary-0.2.12.dist-info/WHEEL
replacy_issue_boundary-0.2.12.dist-info/METADATA
replacy_issue_boundary-0.2.12.dist-info/RECORD
