Metadata-Version: 2.1
Name: replacy-issue-boundary
Version: 0.2.12
Summary: A replaCy component to fix issue boundary, fix signle or double space at start, extend to next word if facing casing issue.
Home-page: https://github.com/Qordobacode/replacy_issue_boundary
License: MIT
Keywords: replacy,spacy,nlp,languagetool
Author: Sam Havens
Author-email: sam.havens@qordoba.com
Requires-Python: >=3.8,<4.0
Classifier: Intended Audience :: Developers
Classifier: Intended Audience :: Science/Research
Classifier: License :: OSI Approved :: MIT License
Classifier: Natural Language :: English
Classifier: Programming Language :: Python :: 3
Classifier: Programming Language :: Python :: 3.8
Classifier: Programming Language :: Python :: 3.9
Classifier: Topic :: Scientific/Engineering :: Artificial Intelligence
Classifier: Topic :: Text Processing :: Linguistic
Classifier: Typing :: Typed
Requires-Dist: importlib_metadata (>=1.7.0,<2.0.0); python_version < "3.8"
Project-URL: Repository, https://github.com/Qordobacode/replacy_issue_boundary
